chatterbot_py/__init__.py
chatterbot_py/__main__.py
chatterbot_py/adapters.py
chatterbot_py/chatterbot.py
chatterbot_py/comparisons.py
chatterbot_py/constants.py
chatterbot_py/conversation.py
chatterbot_py/corpus.py
chatterbot_py/exceptions.py
chatterbot_py/filters.py
chatterbot_py/languages.py
chatterbot_py/parsing.py
chatterbot_py/preprocessors.py
chatterbot_py/response_selection.py
chatterbot_py/search.py
chatterbot_py/tagging.py
chatterbot_py/trainers.py
chatterbot_py/utils.py
chatterbot_py/ext/__init__.py
chatterbot_py/ext/django_chatterbot/__init__.py
chatterbot_py/ext/django_chatterbot/abstract_models.py
chatterbot_py/ext/django_chatterbot/admin.py
chatterbot_py/ext/django_chatterbot/apps.py
chatterbot_py/ext/django_chatterbot/model_admin.py
chatterbot_py/ext/django_chatterbot/models.py
chatterbot_py/ext/django_chatterbot/settings.py
chatterbot_py/ext/django_chatterbot/migrations/0001_initial.py
chatterbot_py/ext/django_chatterbot/migrations/0002_statement_extra_data.py
chatterbot_py/ext/django_chatterbot/migrations/0003_change_occurrence_default.py
chatterbot_py/ext/django_chatterbot/migrations/0004_rename_in_response_to.py
chatterbot_py/ext/django_chatterbot/migrations/0005_statement_created_at.py
chatterbot_py/ext/django_chatterbot/migrations/0006_create_conversation.py
chatterbot_py/ext/django_chatterbot/migrations/0007_response_created_at.py
chatterbot_py/ext/django_chatterbot/migrations/0008_update_conversations.py
chatterbot_py/ext/django_chatterbot/migrations/0009_tags.py
chatterbot_py/ext/django_chatterbot/migrations/0010_statement_text.py
chatterbot_py/ext/django_chatterbot/migrations/0011_blank_extra_data.py
chatterbot_py/ext/django_chatterbot/migrations/0012_statement_created_at.py
chatterbot_py/ext/django_chatterbot/migrations/0013_change_conversations.py
chatterbot_py/ext/django_chatterbot/migrations/0014_remove_statement_extra_data.py
chatterbot_py/ext/django_chatterbot/migrations/0015_statement_persona.py
ChatterBotPy-1.1.3.dist-info/LICENSE
ChatterBotPy-1.1.3.dist-info/METADATA
ChatterBotPy-1.1.3.dist-info/WHEEL
ChatterBotPy-1.1.3.dist-info/top_level.txt
ChatterBotPy-1.1.3.dist-info/zip-safe
ChatterBotPy-1.1.3.dist-info/RECORD
