Metadata-Version: 2.1
Name: ChatterBotPy
Version: 1.1.3
Summary: ChatterBot is a machine learning, conversational dialog engine.
Home-page: https://github.com/gunthercox/ChatterBotPy
Download-URL: https://github.com/gunthercox/ChatterBotPy/tarball/1.1.3
Author: Gunther Cox
Author-email: gunthercx@gmail.com
License: BSD
Project-URL: Documentation, https://chatterbot.readthedocs.io
Keywords: ChatterBot,chatbot,chat,bot
Platform: any
Classifier: Development Status :: 4 - Beta
Classifier: Intended Audience :: Developers
Classifier: License :: OSI Approved :: BSD License
Classifier: Environment :: Console
Classifier: Environment :: Web Environment
Classifier: Operating System :: OS Independent
Classifier: Topic :: Software Development :: Libraries :: Python Modules
Classifier: Topic :: Communications :: Chat
Classifier: Topic :: Internet
Classifier: Programming Language :: Python
Classifier: Programming Language :: Python :: 3
Classifier: Programming Language :: Python :: 3.4
Classifier: Programming Language :: Python :: 3.5
Classifier: Programming Language :: Python :: 3.6
Classifier: Programming Language :: Python :: 3.7
Classifier: Programming Language :: Python :: 3.8
Classifier: Programming Language :: Python :: 3 :: Only
Requires-Python: >=3.4
License-File: LICENSE
Requires-Dist: mathparse <0.2,>=0.1
Requires-Dist: python-dateutil <2.9,>=2.8
Requires-Dist: sqlalchemy <1.4,>=1.3
Requires-Dist: pytz
